setup.py
vtr_utils/__init__.py
vtr_utils/test.py
vtr_utils.egg-info/PKG-INFO
vtr_utils.egg-info/SOURCES.txt
vtr_utils.egg-info/dependency_links.txt
vtr_utils.egg-info/requires.txt
vtr_utils.egg-info/top_level.txt
vtr_utils/crypto/__init__.py
vtr_utils/crypto/test.py
vtr_utils/differ/__init__.py
vtr_utils/differ/test.py
vtr_utils/encoding/__init__.py
vtr_utils/encoding/test.py
vtr_utils/unpack/__init__.py
vtr_utils/unpack/test.py