Metadata-Version: 1.1
Name: vtr-utils
Version: 0.1.0
Summary: Small utilities
Home-page: https://github.com/viatoriche/vtr_utils
Author: viatoriche
Author-email: maxim@via-net.org
License: MIT
Download-URL: https://github.com/viatoriche/vtr_utils/tarball/0.1.0
Platform: UNKNOWN
